{
  "recommended": [
    {
      "characters": ["Ryu Lion"],
      "reason": {
        "en": "{C/Ranger} dps {E/Earth}.",
        "jp": "{C/Ranger} {E/Earth}アタッカー。",
        "kr": "{C/Ranger} {E/Earth} 딜러.",
        "zh": "{C/Ranger} {E/Earth}输出。",
        "fr": "DPS {C/Ranger} {E/Earth}."
      }
    },
    {
      "characters": ["Notia"],
      "reason": {
        "en": "{C/Ranger} sub-dps {E/Earth}.",
        "jp": "{C/Ranger} {E/Earth}サブアタッカー。",
        "kr": "{C/Ranger} {E/Earth} 서브딜러.",
        "zh": "{C/Ranger} {E/Earth}副输出。",
        "fr": "Sub-DPS {C/Ranger} {E/Earth}."
      }
    }
  ],
  "team": {
    "slots": [
      ["Viella", "Saeran", "Monad Eva"],
      ["Ryu Lion", "Demiurge Luna", "Ame", "Kitsune of Eternity Tamamo-no-Mae"],
      ["Notia"],
      ["Kappa", "Tamara", "Hanbyul Lee"]
    ]
  }
}
