{
  "Core Fusion":          { "jp": "コアフュージョン",             "kr": "코어 융합",         "zh": "核心融合" },
  "Demiurge":             { "jp": "デミウルゴス",                 "kr": "데미우르고스",      "zh": "创世之神" },
  "Gnosis":               { "jp": "グノーシス",                   "kr": "그노시스",          "zh": "诺希斯" },
  "Holy Night's Blessing":{ "jp": "聖夜の祝福",                   "kr": "성야의 축복",        "zh": "圣诞夜的祝福" },
  "Kitsune of Eternity":  { "jp": "三世妖狐",                     "kr": "삼세요호",           "zh": "三世妖狐" },
  "Midnight Rush":        { "jp": "ミッドナイトラッシュ",          "kr": "미드나이트 러시",     "zh": "午夜狂潮" },
  "Monad":                { "jp": "モナド",                       "kr": "모나드",             "zh": "单子" },
  "Mystic Sage":          { "jp": "三蔵法師",                     "kr": "삼장법사",           "zh": "三藏法师" },
  "Omega":                { "jp": "オメガ",                       "kr": "오메가",             "zh": "奥米伽" },
  "Poolside Trickster":   { "jp": "プールのトリックスター",        "kr": "풀장의 트릭스터",    "zh": "泳池魔术师" },
  "Summer Knight's Dream":{ "jp": "青雲の志",                     "kr": "청운의 꿈",          "zh": "青云之梦" }
}
