{
  "title": {
    "en": "Sacreed Guardian Special Request Guide",
    "jp": "セイクリッドガーディアン特殊依頼攻略ガイド",
    "kr": "세이크리드 가디언 특수의뢰 공략 가이드",
    "zh": "圣科利德守护者特殊委托攻略指南",
    "fr": "Guide de la Requête spéciale Sacreed Guardian"
  },
  "description": {
    "en": "Strategy guide for Special Request: Ecology Study mission",
    "jp": "特別依頼：生態調査ミッションの攻略ガイド",
    "kr": "특별 의뢰: 생태 조사 미션 공략 가이드",
    "zh": "特殊委托：生态调查任务攻略指南",
    "fr": "Guide de stratégie pour la mission Special Request : Ecology Study"
  },
  "icon": "CLG_Raid_Armor_Light",
  "author": "SADtherobot",
  "updated": "2025-05-01",
  "order": 9,
  "bossId": "404400362",
  "group": "raid_1:SYS_RAID_1_DUNGEON_L"
}
